gempaterkini/__init__.py
latest_earthquake_indonesia_erwin-0.6.dist-info/LICENSE
latest_earthquake_indonesia_erwin-0.6.dist-info/METADATA
latest_earthquake_indonesia_erwin-0.6.dist-info/WHEEL
latest_earthquake_indonesia_erwin-0.6.dist-info/top_level.txt
latest_earthquake_indonesia_erwin-0.6.dist-info/RECORD
