Metadata-Version: 2.1
Name: latest-earthquake-indonesia-erwin
Version: 0.6
Summary: This package will get the latest earthquake from BMKG Meteorology, Climatology, and Geophysical Agency
Home-page: https://github.com/erwin-zulfikar/latest-indonesia-earthquake
Author: Erwin Zulfikar
Author-email: erwin_zulfikar@yahoo.com
Project-URL: Bug Tracker, https://github.com/pypa/sampleproject/issues
Classifier: Programming Language :: Python :: 3
Classifier: License :: OSI Approved :: GNU General Public License v3 (GPLv3)
Classifier: Operating System :: OS Independent
Classifier: Development Status :: 5 - Production/Stable
Requires-Python: >= 3.6
License-File: LICENSE
